MANIFEST.in
README.rst
setup.py
fgdb2postgis/__init__.py
fgdb2postgis/__main__.py
fgdb2postgis/filegdb.py
fgdb2postgis/postgis.py
fgdb2postgis/version.py
fgdb2postgis.egg-info/PKG-INFO
fgdb2postgis.egg-info/SOURCES.txt
fgdb2postgis.egg-info/dependency_links.txt
fgdb2postgis.egg-info/entry_points.txt
fgdb2postgis.egg-info/requires.txt
fgdb2postgis.egg-info/top_level.txt
fgdb2postgis/sql_files/foreign_key_constraints_vw.sql
fgdb2postgis/sql_files/information_schema_views.sql