Metadata-Version: 1.1
Name: fgdb2postgis
Version: 0.3.6
Summary: ESRI file geodatabase to PostGIS converter
Home-page: https://github.com/cartologic/fgdb2postgis
Author: George Ioannou
Author-email: gmioannou@cartologic.com
License: GNU
Keywords: fgdb2postgis
Platform: UNKNOWN
Classifier: Environment :: Console
Classifier: Intended Audience :: Science/Research
Classifier: Programming Language :: Python
Classifier: Topic :: Scientific/Engineering :: GIS
Classifier: Operating System :: Microsoft :: Windows
